transmission/__init__.py
transmission/client.py
transmission/models.py
transmission/py.typed
m4rkw_transmission-0.1.5.dist-info/METADATA
m4rkw_transmission-0.1.5.dist-info/WHEEL
m4rkw_transmission-0.1.5.dist-info/top_level.txt
m4rkw_transmission-0.1.5.dist-info/RECORD
