Metadata-Version: 2.4
Name: m4rkw-transmission
Version: 0.1.5
Summary: db
Author-email: Your Name <your@email.com>
Requires-Dist: requests
